{
  "course_id": "39e469dd-cfc0-4357-be27-be8e6d45b1cf",
  "title": "Web Application Security Basics_full",
  "modules": [
    {
      "title": "Introduction to Web Application Security Fundamentals",
      "theory": "# Introduction to Web Application Security Fundamentals\n\n## Subtopic 1: HTTP Protocol and Request/Response Cycle\n\nThe Hypertext Transfer Protocol (HTTP) is the foundation of the web, enabling communication between clients and servers. It is a request-response protocol, where a client, typically a web browser, sends a request to a server, and the server responds with the requested resources. The HTTP protocol is based on a simple request-response cycle:\n\n1. **Client Request**: The client, usually a web browser, initiates a request to the server by sending an HTTP request message. This message includes a method (e.g., GET, POST, PUT, DELETE), a URL, headers, and optionally, a body.\n\n2. **Server Processing**: The server receives the request, processes it, and generates a response. This may involve retrieving data from a database, performing computations, or executing business logic.\n\n3. **Server Response**: The server sends the response back to the client, including a status code, headers, and a body. The status code indicates the outcome of the request (e.g., 200 OK, 404 Not Found, 500 Internal Server Error).\n\n### HTTP Methods\n\nThe HTTP protocol defines several methods, each with its own purpose:\n\n* **GET**: Retrieve a resource from the server.\n\n* **POST**: Create a new resource on the server.\n\n* **PUT**: Update an existing resource on the server.\n\n* **DELETE**: Delete a resource from the server.\n\n### HTTP Headers\n\nHTTP headers are key-value pairs that provide additional information about the request or response. Some common headers include:\n\n* **Content-Type**: Specifies the format of the request or response body (e.g., application/json, text/html).\n\n* **Authorization**: Provides authentication credentials for the request (e.g., Basic Auth, Bearer Token).\n\n* **Cookie**: Stores session information or other data on the client-side.\n\n## Subtopic 2: Web Application Security Threats and Vulnerabilities\n\nWeb applications are constantly under attack by malicious actors seeking to exploit vulnerabilities and steal sensitive data. Some common web application security threats and vulnerabilities include:\n\n* **SQL Injection**: Injecting malicious SQL code to manipulate database queries.\n\n* **Cross-Site Scripting (XSS)**: Injecting malicious JavaScript code to steal user data or take control of user sessions.\n\n* **Cross-Site Request Forgery (CSRF)**: Tricking users into performing unintended actions on a web application.\n\n* **Buffer Overflow**: Overwriting memory buffers with malicious code to execute arbitrary commands.\n\n### Web Application Security Threats\n\nSome common web application security threats include:\n\n* **Denial of Service (DoS)**: Overwhelming a web application with traffic to make it unavailable.\n\n* **Man-in-the-Middle (MitM)**: Intercepting communication between a client and server to steal sensitive data.\n\n* **Session Hijacking**: Stealing user session cookies to gain unauthorized access to a web application.\n\n## Subtopic 3: Security Basics and Terminology\n\nUnderstanding web application security requires familiarity with key concepts and terminology. Some essential security basics and terminology include:\n\n* **Authentication**: Verifying the identity of users or systems.\n\n* **Authorization**: Controlling access to resources based on user identity or role.\n\n* **Encryption**: Protecting data in transit or at rest using cryptographic algorithms.\n\n* **Firewall**: Blocking unauthorized network traffic to prevent attacks.\n\n### Security Industry Use Cases\n\nWeb application security is crucial in various industries, including:\n\n* **E-commerce**: Protecting customer data and preventing financial fraud.\n\n* **Healthcare**: Safeguarding patient data and preventing medical identity theft.\n\n* **Finance**: Securing financial transactions and preventing cyber attacks.\n\n* **Government**: Protecting sensitive information and preventing cyber espionage.\n\n### Architecture\n\nA secure web application architecture should include:\n\n* **Web Application Firewall (WAF)**: Filtering incoming traffic to prevent attacks.\n\n* **Intrusion Detection System (IDS)**: Monitoring network traffic for signs of unauthorized access.\n\n* **Secure Sockets Layer/Transport Layer Security (SSL/TLS)**: Encrypting data in transit.\n\n* **Load Balancer**: Distributing traffic to prevent overload and ensure availability.\n\n### Security Best Practices\n\nTo ensure web application security, follow these best practices:\n\n* **Validate User Input**: Preventing malicious input from entering the application.\n\n* **Use Secure Protocols**: Encrypting data in transit using HTTPS.\n\n* **Implement Access Control**: Restricting access to sensitive resources.\n\n* **Regularly Update and Patch**: Keeping software and dependencies up-to-date to prevent vulnerabilities.\n\n",
      "code_lab": "Step 1: Set up a web application framework (e.g., Node.js, Django) and create a simple web application.\n\nStep 2: Implement user authentication using a library or framework (e.g., Passport.js, Django Authentication).\n\nStep 3: Protect against SQL injection attacks by using parameterized queries or an Object-Relational Mapping (ORM) tool.\n\nStep 4: Implement CSRF protection using a library or framework (e.g., OWASP CSRFGuard, Django CSRF).\n\nStep 5: Use a web application firewall (WAF) to filter incoming traffic and prevent attacks.\n\nStep 6: Monitor the web application for security vulnerabilities and update dependencies regularly.",
      "prerequisites": [
        "HTTP Protocol",
        "Web Application Security Fundamentals",
        "Programming Language (e.g., Python, JavaScript)"
      ],
      "mcqs": [
        {
          "question": "What is the primary purpose of the HTTP protocol?",
          "options": [
            "To provide a secure connection",
            "To facilitate communication between clients and servers",
            "To manage network traffic",
            "To store data"
          ],
          "answer": "To facilitate communication between clients and servers"
        },
        {
          "question": "What is a common web application security threat?",
          "options": [
            "SQL injection",
            "Cross-site scripting (XSS)",
            "Cross-site request forgery (CSRF)",
            "All of the above"
          ],
          "answer": "All of the above"
        },
        {
          "question": "What is the purpose of encryption in web application security?",
          "options": [
            "To authenticate users",
            "To authorize access to resources",
            "To protect data in transit or at rest",
            "To prevent buffer overflows"
          ],
          "answer": "To protect data in transit or at rest"
        }
      ]
    },
    {
      "title": "Web Application Security Threats and Countermeasures",
      "theory": "```\n{\n  \"title\": \"Web Application Security Threats and Countermeasures\",\n  \"theory\": \"# Web Application Security Threats and Countermeasures\\n## Introduction\\nWeb application security is a critical aspect of protecting online applications from various types of cyber threats. In this module, we will explore three key topics: SQL Injection and Mitigation Techniques, Cross-Site Scripting (XSS) Attacks and Prevention, and Cross-Site Request Forgery (CSRF) and Defense Strategies.\\n## Subtopic 1: SQL Injection and Mitigation Techniques\\n### Concept\\nSQL injection is a type of cyber attack where an attacker injects malicious SQL code into a web application\\'s database in order to extract or modify sensitive data. This can occur when user input is not properly sanitized or validated, allowing an attacker to inject malicious code.\\n### Architecture\\nA typical web application architecture consists of a client-side interface, a server-side application, and a database. When a user submits a request to the application, the application processes the request and interacts with the database to retrieve or update data. If the application does not properly validate user input, an attacker can inject malicious SQL code, which can then be executed by the database.\\n### Security\\nTo prevent SQL injection attacks, it is essential to implement proper input validation and sanitization techniques. This can include using prepared statements, parameterized queries, and escaping user input. Additionally, limiting database privileges and using a web application firewall (WAF) can help prevent SQL injection attacks.\\n### Industry Use Cases\\nSQL injection attacks have been used in various high-profile breaches, including the 2013 Yahoo! breach, where hackers used SQL injection to steal sensitive data. Other notable examples include the 2014 JPMorgan Chase breach and the 2015 TalkTalk breach.\\n## Subtopic 2: Cross-Site Scripting (XSS) Attacks and Prevention\\n### Concept\\nCross-site scripting (XSS) is a type of cyber attack where an attacker injects malicious JavaScript code into a web application, which is then executed by the user\\'s browser. This can occur when user input is not properly sanitized or validated, allowing an attacker to inject malicious code.\\n### Architecture\\nA typical web application architecture consists of a client-side interface, a server-side application, and a database. When a user submits a request to the application, the application processes the request and returns a response to the user\\'s browser. If the application does not properly validate user input, an attacker can inject malicious JavaScript code, which can then be executed by the user\\'s browser.\\n### Security\\nTo prevent XSS attacks, it is essential to implement proper input validation and sanitization techniques. This can include using HTML escaping, JavaScript escaping, and content security policy (CSP). Additionally, limiting user input and using a web application firewall (WAF) can help prevent XSS attacks.\\n### Industry Use Cases\\nXSS attacks have been used in various high-profile breaches, including the 2013 Facebook breach, where hackers used XSS to steal sensitive data. Other notable examples include the 2014 Google breach and the 2015 Twitter breach.\\n## Subtopic 3: Cross-Site Request Forgery (CSRF) and Defense Strategies\\n### Concept\\nCross-site request forgery (CSRF) is a type of cyber attack where an attacker tricks a user into performing an unintended action on a web application. This can occur when an attacker creates a malicious webpage that makes a request to the web application, which is then executed by the user\\'s browser.\\n### Architecture\\nA typical web application architecture consists of a client-side interface, a server-side application, and a database. When a user submits a request to the application, the application processes the request and returns a response to the user\\'s browser. If the application does not properly validate user input, an attacker can create a malicious webpage that makes a request to the application, which can then be executed by the user\\'s browser.\\n### Security\\nTo prevent CSRF attacks, it is essential to implement proper validation and verification techniques. This can include using tokens, headers, and same-site cookies. Additionally, limiting user input and using a web application firewall (WAF) can help prevent CSRF attacks.\\n### Industry Use Cases\\nCSRF attacks have been used in various high-profile breaches, including the 2015 Dropbox breach, where hackers used CSRF to steal sensitive data. Other notable examples include the 2016 Uber breach and the 2017 Equifax breach.\",\n  \"code_lab\": \"## Step 1: Setting up the Environment\\n* Install a web application framework such as Flask or Django\\n* Create a new web application project\\n## Step 2: Implementing SQL Injection Mitigation Techniques\\n* Use prepared statements and parameterized queries to prevent SQL injection\\n* Validate and sanitize user input using HTML escaping and JavaScript escaping\\n## Step 3: Implementing XSS Prevention Techniques\\n* Use HTML escaping and JavaScript escaping to prevent XSS attacks\\n* Implement content security policy (CSP) to define which sources of content are allowed to be executed\\n## Step 4: Implementing CSRF Defense Strategies\\n* Use tokens, headers, and same-site cookies to prevent CSRF attacks\\n* Validate and verify user input using proper validation and verification techniques\",\n  \"prerequisites\": [\"Web Application Security Basics\", \"HTML\", \"JavaScript\", \"SQL\"],\n  \"mcqs\": [\n    {\n      \"question\": \"What is the primary goal of a SQL injection attack?\",\n      \"answers\": [\"To steal sensitive data\", \"To modify database structures\", \"To disrupt database services\", \"To inject malicious code\"],\n      \"correct_answer\": \"To steal sensitive data\"\n    },\n    {\n      \"question\": \"What is the primary goal of a Cross-Site Scripting (XSS) attack?\",\n      \"answers\": [\"To steal sensitive data\", \"To modify database structures\", \"To disrupt database services\", \"To inject malicious JavaScript code\"],\n      \"correct_answer\": \"To inject malicious JavaScript code\"\n    },\n    {\n      \"question\": \"What is the primary goal of a Cross-Site Request Forgery (CSRF) attack?\",\n      \"answers\": [\"To steal sensitive data\", \"To modify database structures\", \"To disrupt database services\", \"To trick a user into performing an unintended action\"],\n      \"correct_answer\": \"To trick a user into performing an unintended action\"\n    }\n  ]\n}\n```",
      "code_lab": "Review full logs for generation details.",
      "prerequisites": [],
      "mcqs": []
    },
    {
      "title": "Secure Coding Practices and Web Application Security Testing",
      "theory": "```\n{\n  \"title\": \"Secure Coding Practices and Web Application Security Testing\",\n  \"theory\": \"# Secure Coding Practices and Web Application Security Testing\\n## Subtopic 1: Secure Coding Guidelines and Best Practices\\nSecure coding practices are essential for developing secure web applications. These practices help prevent common web application vulnerabilities such as SQL injection, cross-site scripting (XSS), and cross-site request forgery (CSRF). The following are some secure coding guidelines and best practices:\\n* **Input Validation**: Validate all user input to prevent malicious data from entering the application.\\n* **Output Encoding**: Encode all output to prevent XSS attacks.\\n* **Error Handling**: Implement proper error handling to prevent information disclosure.\\n* **Secure Password Storage**: Store passwords securely using a strong password hashing algorithm.\\n* **Secure Communication**: Use HTTPS to encrypt communication between the client and server.\\n\\n## Subtopic 2: Web Application Security Testing Methodologies and Tools\\nWeb application security testing is crucial to identify vulnerabilities in the application. The following are some web application security testing methodologies and tools:\\n* **Black Box Testing**: Test the application without knowledge of its internal workings.\\n* **White Box Testing**: Test the application with knowledge of its internal workings.\\n* **Gray Box Testing**: Test the application with some knowledge of its internal workings.\\n* **OWASP ZAP**: An open-source web application security scanner.\\n* **Burp Suite**: A web application security testing tool.\\n\\n## Subtopic 3: Identifying and Exploiting Vulnerabilities using Penetration Testing\\nPenetration testing is a simulated attack on the application to identify vulnerabilities. The following are some steps involved in penetration testing:\\n* **Reconnaissance**: Gather information about the target application.\\n* **Vulnerability Scanning**: Scan the application for vulnerabilities.\\n* **Exploitation**: Exploit the identified vulnerabilities.\\n* **Post-Exploitation**: Perform post-exploitation activities such as privilege escalation and data exfiltration.\\n\\n# Concept\\nThe concept of secure coding practices and web application security testing is to develop secure web applications that can withstand attacks. This concept involves secure coding guidelines and best practices, web application security testing methodologies and tools, and penetration testing.\\n\\n# Architecture\\nThe architecture of secure coding practices and web application security testing involves the following components:\\n* **Secure Coding**: Secure coding practices are implemented during the development phase.\\n* **Web Application Security Testing**: Web application security testing is performed during the testing phase.\\n* **Penetration Testing**: Penetration testing is performed during the deployment phase.\\n\\n# Security\\nThe security of web applications is crucial to prevent attacks. The following are some security measures:\\n* **Authentication**: Implement proper authentication mechanisms.\\n* **Authorization**: Implement proper authorization mechanisms.\\n* **Data Encryption**: Encrypt sensitive data.\\n* **Firewall**: Configure a firewall to block unauthorized access.\\n\\n# Industry Use Cases\\nThe following are some industry use cases for secure coding practices and web application security testing:\\n* **Financial Institutions**: Financial institutions require secure web applications to protect sensitive financial information.\\n* **Healthcare**: Healthcare organizations require secure web applications to protect sensitive patient information.\\n* **E-commerce**: E-commerce websites require secure web applications to protect sensitive customer information.\\n\\nThe importance of secure coding practices and web application security testing cannot be overstated. By following secure coding guidelines and best practices, performing web application security testing, and conducting penetration testing, organizations can develop secure web applications that can withstand attacks.\",\n  \"code_lab\": \"Step-by-step lab instructions:\\\\n1. Set up a web application security testing environment.\\\\n2. Configure OWASP ZAP and Burp Suite.\\\\n3. Perform black box, white box, and gray box testing.\\\\n4. Identify and exploit vulnerabilities using penetration testing.\",\n  \"prerequisites\": [\"Secure Coding Guidelines and Best Practices\", \"Web Application Security Testing Methodologies and Tools\", \"Penetration Testing\"],\n  \"mcqs\": [\n    {\n      \"question\": \"What is the purpose of input validation?\",\n      \"options\": [\"To prevent malicious data from entering the application\", \"To improve application performance\", \"To enhance user experience\"],\n      \"answer\": \"To prevent malicious data from entering the application\"\n    },\n    {\n      \"question\": \"What is the difference between black box and white box testing?\",\n      \"options\": [\"Black box testing is performed without knowledge of the application\\'s internal workings, while white box testing is performed with knowledge of the application\\'s internal workings\", \"Black box testing is performed with knowledge of the application\\'s internal workings, while white box testing is performed without knowledge of the application\\'s internal workings\"],\n      \"answer\": \"Black box testing is performed without knowledge of the application\\'s internal workings, while white box testing is performed with knowledge of the application\\'s internal workings\"\n    },\n    {\n      \"question\": \"What is the purpose of penetration testing?\",\n      \"options\": [\"To identify vulnerabilities in the application\", \"To improve application performance\", \"To enhance user experience\"],\n      \"answer\": \"To identify vulnerabilities in the application\"\n    }\n  ]\n}\n```",
      "code_lab": "Review full logs for generation details.",
      "prerequisites": [],
      "mcqs": []
    },
    {
      "title": "Web Application Security Architecture and Design",
      "theory": "# Web Application Security Architecture and Design\n\n## Subtopic 1: Secure Web Application Architecture Design Patterns\n\nThe design of a web application's architecture is crucial in ensuring the security of the application. A well-designed architecture can help prevent common web application vulnerabilities such as SQL injection and cross-site scripting (XSS). In this subtopic, we will explore secure web application architecture design patterns.\n\n### Concept\n\nA web application's architecture refers to the overall structure and organization of the application's components. This includes the client-side and server-side components, as well as the interactions between them. A secure web application architecture design pattern is one that takes into account the security requirements of the application and is designed to prevent common web application vulnerabilities.\n\n### Architecture\n\nA secure web application architecture typically consists of multiple layers, each with its own set of responsibilities. The most common layers are:\n\n*   **Presentation Layer**: This layer is responsible for handling user input and displaying output to the user. It includes the client-side components such as HTML, CSS, and JavaScript.\n\n*   **Application Layer**: This layer is responsible for handling business logic and interacting with the data storage layer. It includes the server-side components such as Java, Python, and Ruby.\n\n*   **Data Storage Layer**: This layer is responsible for storing and retrieving data. It includes databases such as MySQL, Oracle, and MongoDB.\n\n*   **Network Layer**: This layer is responsible for handling communication between the client and server. It includes protocols such as HTTP and HTTPS.\n\n### Security\n\nA secure web application architecture design pattern should include security measures such as:\n\n*   **Input Validation**: This involves validating user input to prevent common web application vulnerabilities such as SQL injection and XSS.\n\n*   **Authentication and Authorization**: This involves verifying the identity of users and ensuring that they have the necessary permissions to access certain resources.\n\n*   **Data Encryption**: This involves encrypting sensitive data such as passwords and credit card numbers to prevent unauthorized access.\n\n### Industry Use Cases\n\nSecure web application architecture design patterns are used in a variety of industries, including:\n\n*   **Finance**: Secure web application architecture design patterns are used in the finance industry to protect sensitive financial information such as credit card numbers and bank account numbers.\n\n*   **Healthcare**: Secure web application architecture design patterns are used in the healthcare industry to protect sensitive medical information such as patient records and medical histories.\n\n*   **E-commerce**: Secure web application architecture design patterns are used in the e-commerce industry to protect sensitive customer information such as credit card numbers and shipping addresses.\n\n## Subtopic 2: Authentication and Authorization Mechanisms\n\nAuthentication and authorization mechanisms are crucial in ensuring the security of a web application. In this subtopic, we will explore authentication and authorization mechanisms.\n\n### Concept\n\nAuthentication refers to the process of verifying the identity of a user, while authorization refers to the process of verifying that a user has the necessary permissions to access certain resources.\n\n### Architecture\n\nA secure authentication and authorization mechanism typically consists of the following components:\n\n*   **Authentication Server**: This component is responsible for verifying the identity of users.\n\n*   **Authorization Server**: This component is responsible for verifying that users have the necessary permissions to access certain resources.\n\n*   **Client**: This component is responsible for requesting access to resources and providing credentials for authentication and authorization.\n\n### Security\n\nA secure authentication and authorization mechanism should include security measures such as:\n\n*   **Password Hashing**: This involves storing passwords securely using a password hashing algorithm such as bcrypt or scrypt.\n\n*   **Session Management**: This involves managing user sessions securely to prevent session hijacking and fixation attacks.\n\n*   **Access Control**: This involves controlling access to resources based on user roles and permissions.\n\n### Industry Use Cases\n\nAuthentication and authorization mechanisms are used in a variety of industries, including:\n\n*   **Social Media**: Authentication and authorization mechanisms are used in social media platforms to verify the identity of users and control access to resources such as user profiles and posts.\n\n*   **Online Banking**: Authentication and authorization mechanisms are used in online banking systems to verify the identity of users and control access to resources such as account balances and transaction history.\n\n*   **E-commerce**: Authentication and authorization mechanisms are used in e-commerce platforms to verify the identity of users and control access to resources such as order history and payment information.\n\n## Subtopic 3: Input Validation, Sanitization, and Output Encoding Techniques\n\nInput validation, sanitization, and output encoding techniques are crucial in preventing common web application vulnerabilities such as SQL injection and XSS. In this subtopic, we will explore input validation, sanitization, and output encoding techniques.\n\n### Concept\n\nInput validation refers to the process of verifying that user input conforms to expected formats and patterns. Sanitization refers to the process of removing or escaping special characters from user input. Output encoding refers to the process of encoding output to prevent XSS attacks.\n\n### Architecture\n\nA secure input validation, sanitization, and output encoding mechanism typically consists of the following components:\n\n*   **Input Validation Component**: This component is responsible for verifying that user input conforms to expected formats and patterns.\n\n*   **Sanitization Component**: This component is responsible for removing or escaping special characters from user input.\n\n*   **Output Encoding Component**: This component is responsible for encoding output to prevent XSS attacks.\n\n### Security\n\nA secure input validation, sanitization, and output encoding mechanism should include security measures such as:\n\n*   **Whitelisting**: This involves only allowing user input that conforms to expected formats and patterns.\n\n*   **Blacklisting**: This involves removing or escaping special characters from user input.\n\n*   **Output Encoding**: This involves encoding output to prevent XSS attacks.\n\n### Industry Use Cases\n\nInput validation, sanitization, and output encoding techniques are used in a variety of industries, including:\n\n*   **Finance**: Input validation, sanitization, and output encoding techniques are used in the finance industry to protect against SQL injection and XSS attacks.\n\n*   **Healthcare**: Input validation, sanitization, and output encoding techniques are used in the healthcare industry to protect against SQL injection and XSS attacks.\n\n*   **E-commerce**: Input validation, sanitization, and output encoding techniques are used in the e-commerce industry to protect against SQL injection and XSS attacks.",
      "code_lab": "Step-by-step lab instructions: \n1. Create a new web application using a secure framework such as Spring or Django. \n2. Implement input validation, sanitization, and output encoding techniques to prevent SQL injection and XSS attacks. \n3. Implement authentication and authorization mechanisms to verify the identity of users and control access to resources. \n4. Test the web application for common web application vulnerabilities such as SQL injection and XSS.",
      "prerequisites": [
        "Web Application Security Basics",
        "Secure Coding Practices",
        "Web Application Architecture"
      ],
      "mcqs": [
        {
          "question": "What is the primary goal of secure web application architecture design patterns?",
          "options": [
            "To improve performance",
            "To reduce costs",
            "To prevent common web application vulnerabilities",
            "To enhance user experience"
          ],
          "answer": "To prevent common web application vulnerabilities"
        },
        {
          "question": "What is the difference between authentication and authorization?",
          "options": [
            "Authentication verifies the identity of a user, while authorization verifies the permissions of a user",
            "Authentication verifies the permissions of a user, while authorization verifies the identity of a user",
            "Authentication and authorization are the same thing",
            "Authentication is not necessary for authorization"
          ],
          "answer": "Authentication verifies the identity of a user, while authorization verifies the permissions of a user"
        },
        {
          "question": "What is the purpose of input validation, sanitization, and output encoding techniques?",
          "options": [
            "To improve performance",
            "To reduce costs",
            "To prevent SQL injection and XSS attacks",
            "To enhance user experience"
          ],
          "answer": "To prevent SQL injection and XSS attacks"
        }
      ]
    },
    {
      "title": "Advanced Web Application Security Topics and Emerging Threats",
      "theory": "# Advanced Web Application Security Topics and Emerging Threats\n## Subtopic 1: Web Application Firewalls (WAFs) and Content Delivery Networks (CDNs)\n### Concept\nWeb Application Firewalls (WAFs) are a type of security solution that protects web applications from various types of attacks, including SQL injection, cross-site scripting (XSS), and cross-site request forgery (CSRF). A WAF acts as an intermediary between the internet and a web application, analyzing incoming traffic to identify and prevent attacks. Content Delivery Networks (CDNs), on the other hand, are networks of distributed servers that deliver web content to users based on their geographic location. CDNs can also provide an additional layer of security for web applications.\n#### Architecture\nA typical WAF architecture includes the following components:\n*   **Detection Engine**: This component analyzes incoming traffic to identify potential threats.\n*   **Policy Engine**: This component applies security policies to the traffic based on the detection results.\n*   **Logging and Alerting**: This component logs all security events and sends alerts to administrators in case of potential threats.\n#### Security\nWAFs provide several security benefits, including:\n*   **Protection against common web attacks**: WAFs can protect against SQL injection, XSS, and CSRF attacks.\n*   **Protection against zero-day exploits**: WAFs can protect against newly discovered vulnerabilities.\n*   **Compliance with security regulations**: WAFs can help organizations comply with security regulations such as PCI-DSS and HIPAA.\n#### Industry Use Cases\nWAFs are widely used in various industries, including:\n*   **E-commerce**: WAFs are used to protect e-commerce websites from attacks that can lead to financial losses.\n*   **Healthcare**: WAFs are used to protect healthcare websites from attacks that can compromise sensitive patient data.\n*   **Finance**: WAFs are used to protect financial websites from attacks that can lead to financial losses.\n## Subtopic 2: SSL/TLS and Certificate Management\n### Concept\nSSL/TLS (Secure Sockets Layer/Transport Layer Security) is a security protocol that provides end-to-end encryption for web communications. SSL/TLS certificates are used to establish trust between a web server and a client browser. Certificate management refers to the process of obtaining, installing, and renewing SSL/TLS certificates.\n#### Architecture\nA typical SSL/TLS architecture includes the following components:\n*   **Certificate Authority (CA)**: A CA issues SSL/TLS certificates to organizations.\n*   **Certificate Repository**: A certificate repository stores SSL/TLS certificates and their associated private keys.\n*   **Web Server**: A web server uses SSL/TLS certificates to establish secure connections with client browsers.\n#### Security\nSSL/TLS provides several security benefits, including:\n*   **Encryption**: SSL/TLS encrypts data in transit, making it difficult for attackers to intercept and read.\n*   **Authentication**: SSL/TLS certificates verify the identity of a web server, ensuring that users are communicating with the intended server.\n*   **Integrity**: SSL/TLS ensures that data in transit is not tampered with or modified.\n#### Industry Use Cases\nSSL/TLS is widely used in various industries, including:\n*   **E-commerce**: SSL/TLS is used to protect sensitive customer data, such as credit card numbers and personal information.\n*   **Healthcare**: SSL/TLS is used to protect sensitive patient data, such as medical records and personal information.\n*   **Finance**: SSL/TLS is used to protect sensitive financial data, such as account numbers and transaction information.\n## Subtopic 3: Emerging Threats and Trends in Web Application Security, including AI-powered Attacks and Defenses\n### Concept\nEmerging threats and trends in web application security include AI-powered attacks and defenses. AI-powered attacks use machine learning and other AI techniques to launch sophisticated attacks on web applications. AI-powered defenses use machine learning and other AI techniques to detect and prevent AI-powered attacks.\n#### Architecture\nA typical AI-powered defense architecture includes the following components:\n*   **Machine Learning Engine**: A machine learning engine analyzes traffic patterns to identify potential threats.\n*   **Anomaly Detection Engine**: An anomaly detection engine identifies unusual traffic patterns that may indicate an attack.\n*   **Response Engine**: A response engine responds to identified threats by blocking or mitigating the attack.\n#### Security\nAI-powered defenses provide several security benefits, including:\n*   **Improved detection accuracy**: AI-powered defenses can detect attacks with higher accuracy than traditional security solutions.\n*   **Real-time response**: AI-powered defenses can respond to attacks in real-time, reducing the risk of damage.\n*   **Adaptive security**: AI-powered defenses can adapt to new and evolving threats, providing continuous protection.\n#### Industry Use Cases\nAI-powered defenses are widely used in various industries, including:\n*   **E-commerce**: AI-powered defenses are used to protect e-commerce websites from AI-powered attacks.\n*   **Healthcare**: AI-powered defenses are used to protect healthcare websites from AI-powered attacks.\n*   **Finance**: AI-powered defenses are used to protect financial websites from AI-powered attacks.",
      "code_lab": "Step-by-step lab instructions: \n1.  Set up a WAF to protect a web application.\n2.  Configure SSL/TLS certificates for a web server.\n3.  Implement AI-powered defenses to detect and prevent AI-powered attacks.",
      "prerequisites": [
        "Web Application Security Basics",
        "Network Security Fundamentals"
      ],
      "mcqs": [
        {
          "question": "What is the primary function of a Web Application Firewall (WAF)?",
          "options": [
            "To protect against common web attacks",
            "To improve website performance",
            "To provide content delivery",
            "To manage SSL/TLS certificates"
          ],
          "answer": "To protect against common web attacks"
        },
        {
          "question": "What is the purpose of SSL/TLS certificates in web application security?",
          "options": [
            "To establish trust between a web server and a client browser",
            "To encrypt data in transit",
            "To authenticate user credentials",
            "To authorize access to sensitive data"
          ],
          "answer": "To establish trust between a web server and a client browser"
        },
        {
          "question": "What is the primary benefit of using AI-powered defenses in web application security?",
          "options": [
            "Improved detection accuracy",
            "Real-time response",
            "Adaptive security",
            "All of the above"
          ],
          "answer": "All of the above"
        }
      ]
    }
  ]
}